setup.cfg
setup.py
pysform/__init__.py
pysform/element.py
pysform/exceptions.py
pysform/file_upload_translators.py
pysform/form.py
pysform/processors.py
pysform/render.py
pysform/util.py
pysform.egg-info/PKG-INFO
pysform.egg-info/SOURCES.txt
pysform.egg-info/dependency_links.txt
pysform.egg-info/not-zip-safe
pysform.egg-info/requires.txt
pysform.egg-info/top_level.txt