Metadata-Version: 1.0
Name: pysform
Version: 0.2.1
Summary: A library for generating and validating HTML forms
Home-page: http://pypi.python.org/pypi/pysform
Author: Randy Syring
Author-email: rsyring@gmail.com
License: BSD
Platform: UNKNOWN
Classifier: Development Status :: 4 - Beta
Classifier: Intended Audience :: Developers
Classifier: License :: OSI Approved :: BSD License
